ma+h/__init__.py
meth/__init__.py
meth/math_functions.py
meth_math-0.1.0.dist-info/licenses/LICENSE
meth_math-0.1.0.dist-info/METADATA
meth_math-0.1.0.dist-info/WHEEL
meth_math-0.1.0.dist-info/top_level.txt
meth_math-0.1.0.dist-info/RECORD
