Metadata-Version: 2.4
Name: meth-math
Version: 0.1.0
Summary: meth - A simple Python library for mathematical functions
Home-page: https://github.com/yourusername/meth
Author: jhon
Author-email: jhon <adghb@gmail.com>
License: MIT
Project-URL: Homepage, https://github.com/yourusername/meth
Project-URL: Repository, https://github.com/yourusername/meth
Project-URL: Issues, https://github.com/yourusername/meth/issues
Classifier: Development Status :: 3 - Alpha
Classifier: Intended Audience :: Developers
Classifier: License :: OSI Approved :: MIT License
Classifier: Operating System :: OS Independent
Classifier: Programming Language :: Python :: 3
Classifier: Programming Language :: Python :: 3.6
Classifier: Programming Language :: Python :: 3.7
Classifier: Programming Language :: Python :: 3.8
Classifier: Programming Language :: Python :: 3.9
Classifier: Programming Language :: Python :: 3.10
Classifier: Programming Language :: Python :: 3.11
Classifier: Programming Language :: Python :: 3.12
Requires-Python: >=3.6
License-File: LICENSE
Dynamic: author
Dynamic: home-page
Dynamic: license-file
Dynamic: requires-python
